[
  {
    "book": "Exodus",
    "chapter": 20,
    "verse": 1,
    "start": 2.98,
    "end": 5.21
  },
  {
    "book": "Exodus",
    "chapter": 20,
    "verse": 2,
    "start": 5.92,
    "end": 10.97
  },
  {
    "book": "Exodus",
    "chapter": 20,
    "verse": 3,
    "start": 11.849999,
    "end": 13.959999999999999
  },
  {
    "book": "Exodus",
    "chapter": 20,
    "verse": 4,
    "start": 15.5,
    "end": 23.990000000000002
  },
  {
    "book": "Exodus",
    "chapter": 20,
    "verse": 5,
    "start": 24.81,
    "end": 37.41
  },
  {
    "book": "Exodus",
    "chapter": 20,
    "verse": 6,
    "start": 38.15,
    "end": 42.53
  },
  {
    "book": "Exodus",
    "chapter": 20,
    "verse": 7,
    "start": 44.05,
    "end": 50.76
  },
  {
    "book": "Exodus",
    "chapter": 20,
    "verse": 8,
    "start": 52.1,
    "end": 54.159999000000006
  },
  {
    "book": "Exodus",
    "chapter": 20,
    "verse": 9,
    "start": 54.83,
    "end": 57.34
  },
  {
    "book": "Exodus",
    "chapter": 20,
    "verse": 10,
    "start": 57.57,
    "end": 70.48999900000001
  },
  {
    "book": "Exodus",
    "chapter": 20,
    "verse": 11,
    "start": 70.869999,
    "end": 80.14999999999999
  },
  {
    "book": "Exodus",
    "chapter": 20,
    "verse": 12,
    "start": 81.74,
    "end": 86.52
  },
  {
    "book": "Exodus",
    "chapter": 20,
    "verse": 13,
    "start": 86.52,
    "end": 89.359999
  },
  {
    "book": "Exodus",
    "chapter": 20,
    "verse": 14,
    "start": 90.82,
    "end": 92.41
  },
  {
    "book": "Exodus",
    "chapter": 20,
    "verse": 15,
    "start": 93.66,
    "end": 94.72000000000001
  },
  {
    "book": "Exodus",
    "chapter": 20,
    "verse": 16,
    "start": 95.99,
    "end": 98.44999999999999
  },
  {
    "book": "Exodus",
    "chapter": 20,
    "verse": 17,
    "start": 99.969999,
    "end": 110.95
  },
  {
    "book": "Exodus",
    "chapter": 20,
    "verse": 18,
    "start": 112.51,
    "end": 122.52
  },
  {
    "book": "Exodus",
    "chapter": 20,
    "verse": 19,
    "start": 123.44,
    "end": 129.5
  },
  {
    "book": "Exodus",
    "chapter": 20,
    "verse": 20,
    "start": 130.5,
    "end": 137.58
  },
  {
    "book": "Exodus",
    "chapter": 20,
    "verse": 21,
    "start": 138.509999,
    "end": 143.04999999999998
  },
  {
    "book": "Exodus",
    "chapter": 20,
    "verse": 22,
    "start": 143.32,
    "end": 150.25
  },
  {
    "book": "Exodus",
    "chapter": 20,
    "verse": 23,
    "start": 151.2,
    "end": 156.51999999999998
  },
  {
    "book": "Exodus",
    "chapter": 20,
    "verse": 24,
    "start": 157.559999,
    "end": 170.95000000000002
  },
  {
    "book": "Exodus",
    "chapter": 20,
    "verse": 25,
    "start": 171.469999,
    "end": 179.76999899999998
  },
  {
    "book": "Exodus",
    "chapter": 20,
    "verse": 26,
    "start": 180.72,
    "end": 185.82999999999998
  }
]