{
 "fragments": [
  {
   "begin": "0.000",
   "children": [],
   "end": "5.560",
   "id": "f000001",
   "language": "eng",
   "lines": [
    "Chapter twelve"
   ]
  },
  {
   "begin": "5.560",
   "children": [],
   "end": "11.520",
   "id": "f000002",
   "language": "eng",
   "lines": [
    "Now concerning spiritual gifts, brethren, I would not have you ignorant."
   ]
  },
  {
   "begin": "11.520",
   "children": [],
   "end": "18.360",
   "id": "f000003",
   "language": "eng",
   "lines": [
    "Ye know that ye were Gentiles, carried away unto these dumb idols, even as ye were led."
   ]
  },
  {
   "begin": "18.360",
   "children": [],
   "end": "30.640",
   "id": "f000004",
   "language": "eng",
   "lines": [
    "Wherefore I give you to understand, that no man speaking by the Spirit of God calleth Jesus accursed: and that no man can say that Jesus is the Lord, but by the Holy Ghost."
   ]
  },
  {
   "begin": "30.640",
   "children": [],
   "end": "35.160",
   "id": "f000005",
   "language": "eng",
   "lines": [
    "Now there are diversities of gifts, but the same Spirit."
   ]
  },
  {
   "begin": "35.160",
   "children": [],
   "end": "39.760",
   "id": "f000006",
   "language": "eng",
   "lines": [
    "And there are differences of administrations, but the same Lord."
   ]
  },
  {
   "begin": "39.760",
   "children": [],
   "end": "47.160",
   "id": "f000007",
   "language": "eng",
   "lines": [
    "And there are diversities of operations, but it is the same God which worketh all in all."
   ]
  },
  {
   "begin": "47.160",
   "children": [],
   "end": "51.720",
   "id": "f000008",
   "language": "eng",
   "lines": [
    "But the manifestation of the Spirit is given to every man to profit withal."
   ]
  },
  {
   "begin": "51.720",
   "children": [],
   "end": "58.680",
   "id": "f000009",
   "language": "eng",
   "lines": [
    "For to one is given by the Spirit the word of wisdom; to another the word of knowledge by the same Spirit;"
   ]
  },
  {
   "begin": "58.680",
   "children": [],
   "end": "65.240",
   "id": "f000010",
   "language": "eng",
   "lines": [
    "To another faith by the same Spirit; to another the gifts of healing by the same Spirit;"
   ]
  },
  {
   "begin": "65.240",
   "children": [],
   "end": "78.680",
   "id": "f000011",
   "language": "eng",
   "lines": [
    "To another the working of miracles; to another prophecy; to another discerning of spirits; to another divers kinds of tongues; to another the interpretation of tongues:"
   ]
  },
  {
   "begin": "78.680",
   "children": [],
   "end": "86.920",
   "id": "f000012",
   "language": "eng",
   "lines": [
    "But all these worketh that one and the selfsame Spirit, dividing to every man severally as he will."
   ]
  },
  {
   "begin": "86.920",
   "children": [],
   "end": "97.960",
   "id": "f000013",
   "language": "eng",
   "lines": [
    "For as the body is one, and hath many members, and all the members of that one body, being many, are one body: so also is Christ."
   ]
  },
  {
   "begin": "97.960",
   "children": [],
   "end": "110.840",
   "id": "f000014",
   "language": "eng",
   "lines": [
    "For by one Spirit are we all baptized into one body, whether we be Jews or Gentiles, whether we be bond or free; and have been all made to drink into one Spirit."
   ]
  },
  {
   "begin": "110.840",
   "children": [],
   "end": "115.040",
   "id": "f000015",
   "language": "eng",
   "lines": [
    "For the body is not one member, but many."
   ]
  },
  {
   "begin": "115.040",
   "children": [],
   "end": "122.720",
   "id": "f000016",
   "language": "eng",
   "lines": [
    "If the foot shall say, Because I am not the hand, I am not of the body; is it therefore not of the body?"
   ]
  },
  {
   "begin": "122.720",
   "children": [],
   "end": "131.240",
   "id": "f000017",
   "language": "eng",
   "lines": [
    "And if the ear shall say, Because I am not the eye, I am not of the body; is it therefore not of the body?"
   ]
  },
  {
   "begin": "131.240",
   "children": [],
   "end": "140.960",
   "id": "f000018",
   "language": "eng",
   "lines": [
    "If the whole body were an eye, where were the hearing? If the whole were hearing, where were the smelling?"
   ]
  },
  {
   "begin": "140.960",
   "children": [],
   "end": "148.080",
   "id": "f000019",
   "language": "eng",
   "lines": [
    "But now hath God set the members every one of them in the body, as it hath pleased him."
   ]
  },
  {
   "begin": "148.080",
   "children": [],
   "end": "150.680",
   "id": "f000020",
   "language": "eng",
   "lines": [
    "And if they were all one member, where were the body?"
   ]
  },
  {
   "begin": "150.680",
   "children": [],
   "end": "154.640",
   "id": "f000021",
   "language": "eng",
   "lines": [
    "But now are they many members, yet but one body."
   ]
  },
  {
   "begin": "154.640",
   "children": [],
   "end": "162.240",
   "id": "f000022",
   "language": "eng",
   "lines": [
    "And the eye cannot say unto the hand, I have no need of thee: nor again the head to the feet, I have no need of you."
   ]
  },
  {
   "begin": "162.240",
   "children": [],
   "end": "168.440",
   "id": "f000023",
   "language": "eng",
   "lines": [
    "Nay, much more those members of the body, which seem to be more feeble, are necessary:"
   ]
  },
  {
   "begin": "168.440",
   "children": [],
   "end": "178.840",
   "id": "f000024",
   "language": "eng",
   "lines": [
    "And those members of the body, which we think to be less honourable, upon these we bestow more abundant honour; and our uncomely parts have more abundant comeliness."
   ]
  },
  {
   "begin": "178.840",
   "children": [],
   "end": "188.040",
   "id": "f000025",
   "language": "eng",
   "lines": [
    "For our comely parts have no need: but God hath tempered the body together, having given more abundant honour to that part which lacked."
   ]
  },
  {
   "begin": "188.040",
   "children": [],
   "end": "195.880",
   "id": "f000026",
   "language": "eng",
   "lines": [
    "That there should be no schism in the body; but that the members should have the same care one for another."
   ]
  },
  {
   "begin": "195.880",
   "children": [],
   "end": "205.120",
   "id": "f000027",
   "language": "eng",
   "lines": [
    "And whether one member suffer, all the members suffer with it; or one member be honoured, all the members rejoice with it."
   ]
  },
  {
   "begin": "205.120",
   "children": [],
   "end": "209.920",
   "id": "f000028",
   "language": "eng",
   "lines": [
    "Now ye are the body of Christ, and members in particular."
   ]
  },
  {
   "begin": "209.920",
   "children": [],
   "end": "225.760",
   "id": "f000029",
   "language": "eng",
   "lines": [
    "And God hath set some in the church, first apostles, secondarily prophets, thirdly teachers, after that miracles, then gifts of healings, helps, governments, diversities of tongues."
   ]
  },
  {
   "begin": "225.760",
   "children": [],
   "end": "233.480",
   "id": "f000030",
   "language": "eng",
   "lines": [
    "Are all apostles? are all prophets? are all teachers? are all workers of miracles?"
   ]
  },
  {
   "begin": "233.480",
   "children": [],
   "end": "240.280",
   "id": "f000031",
   "language": "eng",
   "lines": [
    "Have all the gifts of healing? do all speak with tongues? do all interpret?"
   ]
  },
  {
   "begin": "240.280",
   "children": [],
   "end": "252.240",
   "id": "f000032",
   "language": "eng",
   "lines": [
    "But covet earnestly the best gifts: and yet shew I unto you a more excellent way."
   ]
  }
 ]
}