[
  {
    "book": "Song of Solomon",
    "chapter": 7,
    "verse": 1,
    "start": 2.34,
    "end": 10.0
  },
  {
    "book": "Song of Solomon",
    "chapter": 7,
    "verse": 2,
    "start": 10.0,
    "end": 17.239999
  },
  {
    "book": "Song of Solomon",
    "chapter": 7,
    "verse": 3,
    "start": 17.41,
    "end": 20.459999999999997
  },
  {
    "book": "Song of Solomon",
    "chapter": 7,
    "verse": 4,
    "start": 20.96,
    "end": 30.880000000000003
  },
  {
    "book": "Song of Solomon",
    "chapter": 7,
    "verse": 5,
    "start": 31.42,
    "end": 38.29
  },
  {
    "book": "Song of Solomon",
    "chapter": 7,
    "verse": 6,
    "start": 39.04,
    "end": 42.029999999999994
  },
  {
    "book": "Song of Solomon",
    "chapter": 7,
    "verse": 7,
    "start": 42.65,
    "end": 47.379999
  },
  {
    "book": "Song of Solomon",
    "chapter": 7,
    "verse": 8,
    "start": 48.059999,
    "end": 58.57
  },
  {
    "book": "Song of Solomon",
    "chapter": 7,
    "verse": 9,
    "start": 59.05,
    "end": 66.80999899999999
  },
  {
    "book": "Song of Solomon",
    "chapter": 7,
    "verse": 10,
    "start": 68.19,
    "end": 71.31
  },
  {
    "book": "Song of Solomon",
    "chapter": 7,
    "verse": 11,
    "start": 71.879999,
    "end": 75.75
  },
  {
    "book": "Song of Solomon",
    "chapter": 7,
    "verse": 12,
    "start": 75.9,
    "end": 84.71
  },
  {
    "book": "Song of Solomon",
    "chapter": 7,
    "verse": 13,
    "start": 85.4,
    "end": 94.89
  }
]