[
  {
    "book": "Ruth",
    "chapter": 3,
    "verse": 1,
    "start": 2.08,
    "end": 7.470000000000001
  },
  {
    "book": "Ruth",
    "chapter": 3,
    "verse": 2,
    "start": 8.01,
    "end": 14.780000000000001
  },
  {
    "book": "Ruth",
    "chapter": 3,
    "verse": 3,
    "start": 15.089999,
    "end": 23.05
  },
  {
    "book": "Ruth",
    "chapter": 3,
    "verse": 4,
    "start": 23.73,
    "end": 33.94
  },
  {
    "book": "Ruth",
    "chapter": 3,
    "verse": 5,
    "start": 35.059999000000005,
    "end": 37.82
  },
  {
    "book": "Ruth",
    "chapter": 3,
    "verse": 6,
    "start": 38.88,
    "end": 42.69
  },
  {
    "book": "Ruth",
    "chapter": 3,
    "verse": 7,
    "start": 43.34,
    "end": 52.22
  },
  {
    "book": "Ruth",
    "chapter": 3,
    "verse": 8,
    "start": 53.709998999999996,
    "end": 60.29
  },
  {
    "book": "Ruth",
    "chapter": 3,
    "verse": 9,
    "start": 60.29,
    "end": 68.999999
  },
  {
    "book": "Ruth",
    "chapter": 3,
    "verse": 10,
    "start": 70.139999,
    "end": 79.77000000000001
  },
  {
    "book": "Ruth",
    "chapter": 3,
    "verse": 11,
    "start": 80.41,
    "end": 87.68
  },
  {
    "book": "Ruth",
    "chapter": 3,
    "verse": 12,
    "start": 88.52,
    "end": 94.54
  },
  {
    "book": "Ruth",
    "chapter": 3,
    "verse": 13,
    "start": 95.74,
    "end": 110.44999999999999
  },
  {
    "book": "Ruth",
    "chapter": 3,
    "verse": 14,
    "start": 111.98,
    "end": 120.10000000000001
  },
  {
    "book": "Ruth",
    "chapter": 3,
    "verse": 15,
    "start": 121.049999,
    "end": 130.37
  },
  {
    "book": "Ruth",
    "chapter": 3,
    "verse": 16,
    "start": 130.92,
    "end": 137.129999
  },
  {
    "book": "Ruth",
    "chapter": 3,
    "verse": 17,
    "start": 138.2,
    "end": 143.74
  },
  {
    "book": "Ruth",
    "chapter": 3,
    "verse": 18,
    "start": 144.75,
    "end": 153.269999
  }
]