[
  {
    "book": "Psalms",
    "chapter": 48,
    "verse": 1,
    "start": 2.67,
    "startOffset": 2,
    "end": 6.96,
    "endOffset": 102
  },
  {
    "book": "Psalms",
    "chapter": 48,
    "verse": 2,
    "start": 7.62,
    "startOffset": 105,
    "end": 14.679999,
    "endOffset": 226
  },
  {
    "book": "Psalms",
    "chapter": 48,
    "verse": 3,
    "start": 15.61,
    "startOffset": 229,
    "end": 17.9,
    "endOffset": 269
  },
  {
    "book": "Psalms",
    "chapter": 48,
    "verse": 4,
    "start": 18.1,
    "startOffset": 272,
    "end": 20.77,
    "endOffset": 330
  },
  {
    "book": "Psalms",
    "chapter": 48,
    "verse": 5,
    "start": 20.92,
    "startOffset": 333,
    "end": 25.049999999999997,
    "endOffset": 404
  },
  {
    "book": "Psalms",
    "chapter": 48,
    "verse": 6,
    "start": 25.6,
    "startOffset": 407,
    "end": 29.36,
    "endOffset": 473
  },
  {
    "book": "Psalms",
    "chapter": 48,
    "verse": 7,
    "start": 29.36,
    "startOffset": 476,
    "end": 32.720000000000006,
    "endOffset": 529
  },
  {
    "book": "Psalms",
    "chapter": 48,
    "verse": 8,
    "start": 33.45,
    "startOffset": 532,
    "end": 40.67,
    "endOffset": 661
  },
  {
    "book": "Psalms",
    "chapter": 48,
    "verse": 9,
    "start": 41.96,
    "startOffset": 664,
    "end": 44.94,
    "endOffset": 736
  },
  {
    "book": "Psalms",
    "chapter": 48,
    "verse": 10,
    "start": 45.41,
    "startOffset": 739,
    "end": 50.96,
    "endOffset": 853
  },
  {
    "book": "Psalms",
    "chapter": 48,
    "verse": 11,
    "start": 51.38,
    "startOffset": 856,
    "end": 55.589999999999996,
    "endOffset": 940
  },
  {
    "book": "Psalms",
    "chapter": 48,
    "verse": 12,
    "start": 56.24,
    "startOffset": 943,
    "end": 60.62,
    "endOffset": 1007
  },
  {
    "book": "Psalms",
    "chapter": 48,
    "verse": 13,
    "start": 61.07,
    "startOffset": 1010,
    "end": 66.64,
    "endOffset": 1106
  },
  {
    "book": "Psalms",
    "chapter": 48,
    "verse": 14,
    "start": 67.389999,
    "startOffset": 1109,
    "end": 73.02,
    "endOffset": 1188
  }
]