[
  {
    "book": "Proverbs",
    "chapter": 5,
    "verse": 1,
    "start": 1.89,
    "end": 5.61
  },
  {
    "book": "Proverbs",
    "chapter": 5,
    "verse": 2,
    "start": 5.98,
    "end": 9.419999
  },
  {
    "book": "Proverbs",
    "chapter": 5,
    "verse": 3,
    "start": 10.83,
    "end": 17.57
  },
  {
    "book": "Proverbs",
    "chapter": 5,
    "verse": 4,
    "start": 18.789999,
    "end": 22.37
  },
  {
    "book": "Proverbs",
    "chapter": 5,
    "verse": 5,
    "start": 22.38,
    "end": 26.78
  },
  {
    "book": "Proverbs",
    "chapter": 5,
    "verse": 6,
    "start": 26.78,
    "end": 32.81999999999999
  },
  {
    "book": "Proverbs",
    "chapter": 5,
    "verse": 7,
    "start": 32.82,
    "end": 37.71
  },
  {
    "book": "Proverbs",
    "chapter": 5,
    "verse": 8,
    "start": 37.71,
    "end": 42.17999999999999
  },
  {
    "book": "Proverbs",
    "chapter": 5,
    "verse": 9,
    "start": 42.18,
    "end": 45.940000000000005
  },
  {
    "book": "Proverbs",
    "chapter": 5,
    "verse": 10,
    "start": 45.94,
    "end": 50.9
  },
  {
    "book": "Proverbs",
    "chapter": 5,
    "verse": 11,
    "start": 50.9,
    "end": 55.33
  },
  {
    "book": "Proverbs",
    "chapter": 5,
    "verse": 12,
    "start": 55.33,
    "end": 61.32
  },
  {
    "book": "Proverbs",
    "chapter": 5,
    "verse": 13,
    "start": 61.32,
    "end": 66.61
  },
  {
    "book": "Proverbs",
    "chapter": 5,
    "verse": 14,
    "start": 66.61,
    "end": 70.9
  },
  {
    "book": "Proverbs",
    "chapter": 5,
    "verse": 15,
    "start": 70.9,
    "end": 79.81
  },
  {
    "book": "Proverbs",
    "chapter": 5,
    "verse": 16,
    "start": 79.82,
    "end": 84.08
  },
  {
    "book": "Proverbs",
    "chapter": 5,
    "verse": 17,
    "start": 84.08,
    "end": 88.21
  },
  {
    "book": "Proverbs",
    "chapter": 5,
    "verse": 18,
    "start": 88.219999,
    "end": 93.19000000000001
  },
  {
    "book": "Proverbs",
    "chapter": 5,
    "verse": 19,
    "start": 93.19,
    "end": 104.66
  },
  {
    "book": "Proverbs",
    "chapter": 5,
    "verse": 20,
    "start": 104.679999,
    "end": 111.32
  },
  {
    "book": "Proverbs",
    "chapter": 5,
    "verse": 21,
    "start": 111.32,
    "end": 118.48
  },
  {
    "book": "Proverbs",
    "chapter": 5,
    "verse": 22,
    "start": 118.5,
    "end": 125.92
  },
  {
    "book": "Proverbs",
    "chapter": 5,
    "verse": 23,
    "start": 125.92,
    "end": 132.02
  }
]