[
  {
    "book": "Acts",
    "chapter": 7,
    "verse": 1,
    "start": 2.7,
    "end": 5.87
  },
  {
    "book": "Acts",
    "chapter": 7,
    "verse": 2,
    "start": 6.91,
    "end": 17.009999000000004
  },
  {
    "book": "Acts",
    "chapter": 7,
    "verse": 3,
    "start": 18.289999,
    "end": 25.040000000000003
  },
  {
    "book": "Acts",
    "chapter": 7,
    "verse": 4,
    "start": 25.21,
    "end": 34.499999
  },
  {
    "book": "Acts",
    "chapter": 7,
    "verse": 5,
    "start": 35.35,
    "end": 46.29
  },
  {
    "book": "Acts",
    "chapter": 7,
    "verse": 6,
    "start": 47.28,
    "end": 56.92
  },
  {
    "book": "Acts",
    "chapter": 7,
    "verse": 7,
    "start": 57.77,
    "end": 65.87
  },
  {
    "book": "Acts",
    "chapter": 7,
    "verse": 8,
    "start": 66.61,
    "end": 78.46
  },
  {
    "book": "Acts",
    "chapter": 7,
    "verse": 9,
    "start": 79.24,
    "end": 84.74
  },
  {
    "book": "Acts",
    "chapter": 7,
    "verse": 10,
    "start": 84.889999,
    "end": 92.76
  },
  {
    "book": "Acts",
    "chapter": 7,
    "verse": 11,
    "start": 94.94,
    "end": 103.06
  },
  {
    "book": "Acts",
    "chapter": 7,
    "verse": 12,
    "start": 104.07,
    "end": 108.209999
  },
  {
    "book": "Acts",
    "chapter": 7,
    "verse": 13,
    "start": 109.16,
    "end": 115.58
  },
  {
    "book": "Acts",
    "chapter": 7,
    "verse": 14,
    "start": 116.49,
    "end": 121.83
  },
  {
    "book": "Acts",
    "chapter": 7,
    "verse": 15,
    "start": 122.009999,
    "end": 126.05
  },
  {
    "book": "Acts",
    "chapter": 7,
    "verse": 16,
    "start": 126.299999,
    "end": 134.34
  },
  {
    "book": "Acts",
    "chapter": 7,
    "verse": 17,
    "start": 135.19,
    "end": 141.29999999999998
  },
  {
    "book": "Acts",
    "chapter": 7,
    "verse": 18,
    "start": 141.82,
    "end": 144.59
  },
  {
    "book": "Acts",
    "chapter": 7,
    "verse": 19,
    "start": 145.33,
    "end": 153.299999
  },
  {
    "book": "Acts",
    "chapter": 7,
    "verse": 20,
    "start": 153.95,
    "end": 160.51
  },
  {
    "book": "Acts",
    "chapter": 7,
    "verse": 21,
    "start": 161.07,
    "end": 165.95
  },
  {
    "book": "Acts",
    "chapter": 7,
    "verse": 22,
    "start": 167.05,
    "end": 173.0
  },
  {
    "book": "Acts",
    "chapter": 7,
    "verse": 23,
    "start": 173.87,
    "end": 179.20000000000002
  },
  {
    "book": "Acts",
    "chapter": 7,
    "verse": 24,
    "start": 180.09,
    "end": 186.58
  },
  {
    "book": "Acts",
    "chapter": 7,
    "verse": 25,
    "start": 187.44,
    "end": 193.82
  },
  {
    "book": "Acts",
    "chapter": 7,
    "verse": 26,
    "start": 194.77,
    "end": 202.35
  },
  {
    "book": "Acts",
    "chapter": 7,
    "verse": 27,
    "start": 203.28,
    "end": 208.44
  },
  {
    "book": "Acts",
    "chapter": 7,
    "verse": 28,
    "start": 208.59,
    "end": 210.96
  },
  {
    "book": "Acts",
    "chapter": 7,
    "verse": 29,
    "start": 212.04,
    "end": 218.08
  },
  {
    "book": "Acts",
    "chapter": 7,
    "verse": 30,
    "start": 219.24,
    "end": 227.22
  },
  {
    "book": "Acts",
    "chapter": 7,
    "verse": 31,
    "start": 228.04,
    "end": 233.78
  },
  {
    "book": "Acts",
    "chapter": 7,
    "verse": 32,
    "start": 233.779999,
    "end": 243.79
  },
  {
    "book": "Acts",
    "chapter": 7,
    "verse": 33,
    "start": 244.77,
    "end": 251.88000000000002
  },
  {
    "book": "Acts",
    "chapter": 7,
    "verse": 34,
    "start": 253.119999,
    "end": 265.90000000000003
  },
  {
    "book": "Acts",
    "chapter": 7,
    "verse": 35,
    "start": 268.049999,
    "end": 279.249999
  },
  {
    "book": "Acts",
    "chapter": 7,
    "verse": 36,
    "start": 279.88,
    "end": 286.5
  },
  {
    "book": "Acts",
    "chapter": 7,
    "verse": 37,
    "start": 287.49,
    "end": 296.7
  },
  {
    "book": "Acts",
    "chapter": 7,
    "verse": 38,
    "start": 297.83,
    "end": 308.15000000000003
  },
  {
    "book": "Acts",
    "chapter": 7,
    "verse": 39,
    "start": 308.7,
    "end": 314.65999999999997
  },
  {
    "book": "Acts",
    "chapter": 7,
    "verse": 40,
    "start": 315.01,
    "end": 323.029999
  },
  {
    "book": "Acts",
    "chapter": 7,
    "verse": 41,
    "start": 323.940001,
    "end": 330.05
  },
  {
    "book": "Acts",
    "chapter": 7,
    "verse": 42,
    "start": 331.74,
    "end": 347.34
  },
  {
    "book": "Acts",
    "chapter": 7,
    "verse": 43,
    "start": 348.17,
    "end": 360.72999899999996
  },
  {
    "book": "Acts",
    "chapter": 7,
    "verse": 44,
    "start": 361.56,
    "end": 369.15
  },
  {
    "book": "Acts",
    "chapter": 7,
    "verse": 45,
    "start": 369.94,
    "end": 380.02
  },
  {
    "book": "Acts",
    "chapter": 7,
    "verse": 46,
    "start": 380.76,
    "end": 385.45
  },
  {
    "book": "Acts",
    "chapter": 7,
    "verse": 47,
    "start": 386.559999,
    "end": 388.629999
  },
  {
    "book": "Acts",
    "chapter": 7,
    "verse": 48,
    "start": 388.639999,
    "end": 395.89
  },
  {
    "book": "Acts",
    "chapter": 7,
    "verse": 49,
    "start": 396.61,
    "end": 404.74
  },
  {
    "book": "Acts",
    "chapter": 7,
    "verse": 50,
    "start": 404.97,
    "end": 407.94999900000005
  },
  {
    "book": "Acts",
    "chapter": 7,
    "verse": 51,
    "start": 410.74,
    "end": 420.52000000000004
  },
  {
    "book": "Acts",
    "chapter": 7,
    "verse": 52,
    "start": 421.78,
    "end": 431.61999999999995
  },
  {
    "book": "Acts",
    "chapter": 7,
    "verse": 53,
    "start": 431.76,
    "end": 435.54
  },
  {
    "book": "Acts",
    "chapter": 7,
    "verse": 54,
    "start": 437.03,
    "end": 441.33
  },
  {
    "book": "Acts",
    "chapter": 7,
    "verse": 55,
    "start": 441.809999,
    "end": 449.33
  },
  {
    "book": "Acts",
    "chapter": 7,
    "verse": 56,
    "start": 449.529999,
    "end": 455.12
  },
  {
    "book": "Acts",
    "chapter": 7,
    "verse": 57,
    "start": 456.23,
    "end": 461.119999
  },
  {
    "book": "Acts",
    "chapter": 7,
    "verse": 58,
    "start": 461.23,
    "end": 468.94
  },
  {
    "book": "Acts",
    "chapter": 7,
    "verse": 59,
    "start": 469.82,
    "end": 475.03999999999996
  },
  {
    "book": "Acts",
    "chapter": 7,
    "verse": 60,
    "start": 475.8,
    "end": 484.319999
  }
]