[
  {
    "book": "1 Kings",
    "chapter": 5,
    "verse": 1,
    "start": 2.13,
    "end": 9.94
  },
  {
    "book": "1 Kings",
    "chapter": 5,
    "verse": 2,
    "start": 10.69,
    "end": 12.459999
  },
  {
    "book": "1 Kings",
    "chapter": 5,
    "verse": 3,
    "start": 12.799999,
    "end": 21.71
  },
  {
    "book": "1 Kings",
    "chapter": 5,
    "verse": 4,
    "start": 22.23,
    "end": 28.19
  },
  {
    "book": "1 Kings",
    "chapter": 5,
    "verse": 5,
    "start": 28.96,
    "end": 40.989999999999995
  },
  {
    "book": "1 Kings",
    "chapter": 5,
    "verse": 6,
    "start": 42.01,
    "end": 57.910000000000004
  },
  {
    "book": "1 Kings",
    "chapter": 5,
    "verse": 7,
    "start": 59.3,
    "end": 68.21
  },
  {
    "book": "1 Kings",
    "chapter": 5,
    "verse": 8,
    "start": 68.75,
    "end": 76.71000000000001
  },
  {
    "book": "1 Kings",
    "chapter": 5,
    "verse": 9,
    "start": 77.45,
    "end": 91.97
  },
  {
    "book": "1 Kings",
    "chapter": 5,
    "verse": 10,
    "start": 93.02,
    "end": 97.08
  },
  {
    "book": "1 Kings",
    "chapter": 5,
    "verse": 11,
    "start": 97.67,
    "end": 106.80000000000001
  },
  {
    "book": "1 Kings",
    "chapter": 5,
    "verse": 12,
    "start": 107.82,
    "end": 114.19
  },
  {
    "book": "1 Kings",
    "chapter": 5,
    "verse": 13,
    "start": 114.9,
    "end": 119.709999
  },
  {
    "book": "1 Kings",
    "chapter": 5,
    "verse": 14,
    "start": 120.49,
    "end": 128.46
  },
  {
    "book": "1 Kings",
    "chapter": 5,
    "verse": 15,
    "start": 129.23,
    "end": 135.29999999999998
  },
  {
    "book": "1 Kings",
    "chapter": 5,
    "verse": 16,
    "start": 135.719999,
    "end": 142.28
  },
  {
    "book": "1 Kings",
    "chapter": 5,
    "verse": 17,
    "start": 143.09,
    "end": 150.79
  },
  {
    "book": "1 Kings",
    "chapter": 5,
    "verse": 18,
    "start": 151.52,
    "end": 159.23
  }
]