{
 "fragments": [
  {
   "begin": "0.000",
   "children": [],
   "end": "1.920",
   "id": "f000001",
   "language": "eng",
   "lines": [
    "Chapter three"
   ]
  },
  {
   "begin": "1.920",
   "children": [],
   "end": "7.320",
   "id": "f000002",
   "language": "eng",
   "lines": [
    "Lord, how are they increased that trouble me! many are they that rise up against me."
   ]
  },
  {
   "begin": "7.320",
   "children": [],
   "end": "13.240",
   "id": "f000003",
   "language": "eng",
   "lines": [
    "Many there be which say of my soul, There is no help for him in God. Selah."
   ]
  },
  {
   "begin": "13.240",
   "children": [],
   "end": "18.440",
   "id": "f000004",
   "language": "eng",
   "lines": [
    "But thou, O LORD, art a shield for me; my glory, and the lifter up of mine head."
   ]
  },
  {
   "begin": "18.440",
   "children": [],
   "end": "24.040",
   "id": "f000005",
   "language": "eng",
   "lines": [
    "I cried unto the LORD with my voice, and he heard me out of his holy hill. Selah."
   ]
  },
  {
   "begin": "24.040",
   "children": [],
   "end": "28.480",
   "id": "f000006",
   "language": "eng",
   "lines": [
    "I laid me down and slept; I awaked; for the LORD sustained me."
   ]
  },
  {
   "begin": "28.480",
   "children": [],
   "end": "33.680",
   "id": "f000007",
   "language": "eng",
   "lines": [
    "I will not be afraid of ten thousands of people, that have set themselves against me round about."
   ]
  },
  {
   "begin": "33.680",
   "children": [],
   "end": "42.920",
   "id": "f000008",
   "language": "eng",
   "lines": [
    "Arise, O LORD; save me, O my God: for thou hast smitten all mine enemies upon the cheek bone; thou hast broken the teeth of the ungodly."
   ]
  },
  {
   "begin": "42.920",
   "children": [],
   "end": "49.760",
   "id": "f000009",
   "language": "eng",
   "lines": [
    "Salvation belongeth unto the LORD: thy blessing is upon thy people. Selah."
   ]
  }
 ]
}