{
 "fragments": [
  {
   "begin": "0.000",
   "children": [],
   "end": "3.440",
   "id": "f000001",
   "language": "eng",
   "lines": [
    "Chapter seventy-one"
   ]
  },
  {
   "begin": "3.440",
   "children": [],
   "end": "8.120",
   "id": "f000002",
   "language": "eng",
   "lines": [
    "In thee, O LORD, do I put my trust: let me never be put to confusion."
   ]
  },
  {
   "begin": "8.120",
   "children": [],
   "end": "13.640",
   "id": "f000003",
   "language": "eng",
   "lines": [
    "Deliver me in thy righteousness, and cause me to escape: incline thine ear unto me, and save me."
   ]
  },
  {
   "begin": "13.640",
   "children": [],
   "end": "22.840",
   "id": "f000004",
   "language": "eng",
   "lines": [
    "Be thou my strong habitation, whereunto I may continually resort: thou hast given commandment to save me; for thou art my rock and my fortress."
   ]
  },
  {
   "begin": "22.840",
   "children": [],
   "end": "27.680",
   "id": "f000005",
   "language": "eng",
   "lines": [
    "Deliver me, O my God, out of the hand of the wicked, out of the hand of the unrighteous and cruel man."
   ]
  },
  {
   "begin": "27.680",
   "children": [],
   "end": "31.600",
   "id": "f000006",
   "language": "eng",
   "lines": [
    "For thou art my hope, O Lord GOD: thou art my trust from my youth."
   ]
  },
  {
   "begin": "31.600",
   "children": [],
   "end": "39.840",
   "id": "f000007",
   "language": "eng",
   "lines": [
    "By thee have I been holden up from the womb: thou art he that took me out of my mother's bowels: my praise shall be continually of thee."
   ]
  },
  {
   "begin": "39.840",
   "children": [],
   "end": "44.040",
   "id": "f000008",
   "language": "eng",
   "lines": [
    "I am as a wonder unto many; but thou art my strong refuge."
   ]
  },
  {
   "begin": "44.040",
   "children": [],
   "end": "47.240",
   "id": "f000009",
   "language": "eng",
   "lines": [
    "Let my mouth be filled with thy praise and with thy honour all the day."
   ]
  },
  {
   "begin": "47.240",
   "children": [],
   "end": "53.600",
   "id": "f000010",
   "language": "eng",
   "lines": [
    "Cast me not off in the time of old age; forsake me not when my strength faileth."
   ]
  },
  {
   "begin": "53.600",
   "children": [],
   "end": "58.520",
   "id": "f000011",
   "language": "eng",
   "lines": [
    "For mine enemies speak against me; and they that lay wait for my soul take counsel together,"
   ]
  },
  {
   "begin": "58.520",
   "children": [],
   "end": "64.520",
   "id": "f000012",
   "language": "eng",
   "lines": [
    "Saying, God hath forsaken him: persecute and take him; for there is none to deliver him."
   ]
  },
  {
   "begin": "64.520",
   "children": [],
   "end": "70.600",
   "id": "f000013",
   "language": "eng",
   "lines": [
    "O God, be not far from me: O my God, make haste for my help."
   ]
  },
  {
   "begin": "70.600",
   "children": [],
   "end": "77.880",
   "id": "f000014",
   "language": "eng",
   "lines": [
    "Let them be confounded and consumed that are adversaries to my soul; let them be covered with reproach and dishonour that seek my hurt."
   ]
  },
  {
   "begin": "77.880",
   "children": [],
   "end": "82.200",
   "id": "f000015",
   "language": "eng",
   "lines": [
    "But I will hope continually, and will yet praise thee more and more."
   ]
  },
  {
   "begin": "82.200",
   "children": [],
   "end": "89.040",
   "id": "f000016",
   "language": "eng",
   "lines": [
    "My mouth shall shew forth thy righteousness and thy salvation all the day; for I know not the numbers thereof."
   ]
  },
  {
   "begin": "89.040",
   "children": [],
   "end": "95.520",
   "id": "f000017",
   "language": "eng",
   "lines": [
    "I will go in the strength of the Lord GOD: I will make mention of thy righteousness, even of thine only."
   ]
  },
  {
   "begin": "95.520",
   "children": [],
   "end": "101.080",
   "id": "f000018",
   "language": "eng",
   "lines": [
    "O God, thou hast taught me from my youth: and hitherto have I declared thy wondrous works."
   ]
  },
  {
   "begin": "101.080",
   "children": [],
   "end": "111.480",
   "id": "f000019",
   "language": "eng",
   "lines": [
    "Now also when I am old and greyheaded, O God, forsake me not; until I have shewed thy strength unto this generation, and thy power to every one that is to come."
   ]
  },
  {
   "begin": "111.480",
   "children": [],
   "end": "119.360",
   "id": "f000020",
   "language": "eng",
   "lines": [
    "Thy righteousness also, O God, is very high, who hast done great things: O God, who is like unto thee!"
   ]
  },
  {
   "begin": "119.360",
   "children": [],
   "end": "128.520",
   "id": "f000021",
   "language": "eng",
   "lines": [
    "Thou, which hast shewed me great and sore troubles, shalt quicken me again, and shalt bring me up again from the depths of the earth."
   ]
  },
  {
   "begin": "128.520",
   "children": [],
   "end": "132.960",
   "id": "f000022",
   "language": "eng",
   "lines": [
    "Thou shalt increase my greatness, and comfort me on every side."
   ]
  },
  {
   "begin": "132.960",
   "children": [],
   "end": "141.200",
   "id": "f000023",
   "language": "eng",
   "lines": [
    "I will also praise thee with the psaltery, even thy truth, O my God: unto thee will I sing with the harp, O thou Holy One of Israel."
   ]
  },
  {
   "begin": "141.200",
   "children": [],
   "end": "146.960",
   "id": "f000024",
   "language": "eng",
   "lines": [
    "My lips shall greatly rejoice when I sing unto thee; and my soul, which thou hast redeemed."
   ]
  },
  {
   "begin": "146.960",
   "children": [],
   "end": "157.120",
   "id": "f000025",
   "language": "eng",
   "lines": [
    "My tongue also shall talk of thy righteousness all the day long: for they are confounded, for they are brought unto shame, that seek my hurt."
   ]
  }
 ]
}